pubmedmcp/__init__.py
pubmedmcp/__main__.py
pubmedmcp-0.1.4.dist-info/METADATA
pubmedmcp-0.1.4.dist-info/WHEEL
pubmedmcp-0.1.4.dist-info/entry_points.txt
pubmedmcp-0.1.4.dist-info/licenses/LICENSE
pubmedmcp-0.1.4.dist-info/RECORD
