Metadata-Version: 2.4
Name: pubmedmcp
Version: 0.1.4
Summary: A MCP server for PubMed data
License-File: LICENSE
Requires-Python: >=3.12
Requires-Dist: mcp>=1.13.1
Requires-Dist: pubmedclient>=0.2.0
